replbase/__init__.py
replbase/cli.py
replbase/cmd_meta.py
replbase/repl_base.py
replbase-0.0.75.dist-info/LICENSE
replbase-0.0.75.dist-info/METADATA
replbase-0.0.75.dist-info/WHEEL
replbase-0.0.75.dist-info/entry_points.txt
replbase-0.0.75.dist-info/RECORD
